freedom-0.0.1.dist-info/RECORD
freedom-0.0.1.dist-info/METADATA
freedom-0.0.1.dist-info/WHEEL
freedom-0.0.1.dist-info/top_level.txt
freedom-0.0.1.dist-info/DESCRIPTION.rst
freedom-0.0.1.dist-info/metadata.json
tests/api/test_tag.py
tests/api/test_release.py
tests/api/test_build.py
tests/api/__init__.py
tests/api/test_upload.py
freedom/task.py
freedom/cli.py
freedom/history.py
freedom/logger.py
freedom/vcs.py
freedom/api.py
freedom/__init__.py
freedom/core.py
freedom/builder.py
freedom/actions.py
freedom/defaults.py
freedom/version.py
freedom/utils.py
freedom/errors.py
freedom/profiles.py
freedom/export.py
freedom/publish.py
