Metadata-Version: 2.0
Name: freedom
Version: 0.0.1
Summary: A pure-python git and pypi release management tool
Home-page: https://bitbucket.org/sys-git/releaseme
Author: Francis Horsman
Author-email: francis.horsman@gmail.com
License: UNKNOWN
Keywords: Python release management
Platform: any
Classifier: Development Status :: 3 - Alpha
Classifier: Intended Audience :: Developers
Classifier: License :: OSI Approved :: GNU General Public License v3 (GPLv3)
Classifier: Operating System :: OS Independent
Classifier: Programming Language :: Python
Classifier: Topic :: Software Development :: Libraries :: Python Modules
Classifier: Programming Language :: Python :: 2.6
Classifier: Programming Language :: Python :: 2.7
Classifier: Programming Language :: Python :: 3.0
Classifier: Programming Language :: Python :: 3.1
Classifier: Programming Language :: Python :: 3.2
Classifier: Programming Language :: Python :: 3.3
Classifier: Programming Language :: Python :: 3.4
Classifier: Programming Language :: Python :: Implementation :: CPython
Requires-Dist: sh (==1.11)
Requires-Dist: click (==3.3)
Requires-Dist: pyyaml (==3.11)
Requires-Dist: nose (==1.3.1)
Requires-Dist: coverage (==3.7.1)
Requires-Dist: tox (==1.8)
Requires-Dist: gitpython (==0.3.4)
Requires-Dist: sphinx (==1.2.3)
Requires-Dist: sphinx-pypi-upload (==0.2.1)
Requires-Dist: ujson (==1.33)
Requires-Dist: msgpack-python (==0.4.4)
Requires-Dist: six (==1.9.0)
Requires-Dist: flake8 (==2.3.0)
Requires-Dist: pylint (==1.4.0)
